/*
 * Jacobin VM - A Java virtual machine
 * Copyright (c) 2021 by Andrew Binstock. All rights reserved.
 * Licensed under Mozilla Public License 2.0 (MPL 2.0)
 */

package exec

const AALOAD = 0x32
const AASTORE = 0x53
const ACONST_NULL = 0x01
const ALOAD = 0x19
const ALOAD_0 = 0x2a
const ALOAD_1 = 0x2b
const ALOAD_2 = 0x2c
const ALOAD_3 = 0x2d
const ANEWARRAY = 0xbd
const ARETURN = 0xb0
const ARRAYLENGTH = 0xbe
const ASTORE = 0x53
const ASTORE_0 = 0x4b
const ASTORE_1 = 0x4c
const ASTORE_2 = 0x4d
const ASTORE_3 = 0x4e
const ATHROW = 0xbf
const BALOAD = 0x33
const BASTORE = 0x54
const BIPUSH = 0x10
const BREAKPOINT = 0xca
const CALOAD = 0x34
const CASTORE = 0x55
const CHECKCAST = 0xc0
const D2F = 0x90
const D2I = 0x8e
const D2L = 0x8f
const DADD = 0x63
const DALOAD = 0x31
const DASTORE = 0x52
const DCMPG = 0x98
const DCMPL = 0x97
const DCONST_0 = 0x0e
const DCONST_1 = 0x0f
const DDIV = 0x6f
const DLOAD = 0x18
const DLOAD_0 = 0x26
const DLOAD_1 = 0x27
const DLOAD_2 = 0x28
const DLOAD_3 = 0x29
const DMUL = 0x6b
const DNEG = 0x77
const DREM = 0x73
const DRETURN = 0xaf
const DSTORE = 0x39
const DSTORE_0 = 0x47
const DSTORE_1 = 0x48
const DSTORE_2 = 0x49
const DSTORE_3 = 0x4a
const DSUB = 0x67
const DUP = 0x59
const DUP_X1 = 0x5a
const DUP_X2 = 0x5b
const DUP2 = 0x5c
const DUP2_X1 = 0x5d
const DUP2_X2 = 0x5e
const F2D = 0x8d
const F2I = 0x8b
const F2L = 0x8c
const FADD = 0x62
const FALOAD = 0x30
const FASTORE = 0x51
const FCMPG = 0x96
const FCMPL = 0x95
const FCONST_0 = 0x0b
const FCONST_1 = 0x0c
const FCONST_2 = 0x0d
const FDIV = 0x6e
const FLOAD = 0x17
const FLOAD_0 = 0x22
const FLOAD_1 = 0x23
const FLOAD_2 = 0x24
const FLOAD_3 = 0x25
const FMUL = 0x6a
const FNEG = 0x76
const FREM = 0x72
const FRETURN = 0xae
const FSTORE = 0x38
const FSTORE_0 = 0x43
const FSTORE_1 = 0x44
const FSTORE_2 = 0x45
const FSTORE_3 = 0x46
const FSUB = 0x66
const GETFIELD = 0xb4
const GETSTATIC = 0xb2
const GOTO = 0xa7
const GOTO_W = 0xc8
const I2B = 0x91
const I2C = 0x92
const I2D = 0x87
const I2F = 0x86
const I2L = 0x85
const I2S = 0x93
const IADD = 0x60
const IALOAD = 0x2e
const IAND = 0x7e
const IASTORE = 0x4f
const ICONST_M1 = 0x02
const ICONST_0 = 0x03
const ICONST_1 = 0x04
const ICONST_2 = 0x05
const ICONST_3 = 0x06
const ICONST_4 = 0x07
const ICONST_5 = 0x08
const IDIV = 0x6c
const IF_ACMPEQ = 0xa5
const IF_ACMPNE = 0xa6
const IF_ICMPEQ = 0x9f
const IF_ICMPGE = 0xa2
const IF_ICMPGT = 0xa3
const IF_ICMPLE = 0xa4
const IF_ICMPLT = 0xa1
const IF_ICMPNE = 0xa0
const IFEQ = 0x99
const IFGE = 0x9c
const IFGT = 0x9d
const IFLE = 0x9e
const IFLT = 0x9b
const IFNE = 0x9a
const IFNONNULL = 0xc7
const IFNULL = 0xc6
const IINC = 0x84
const ILOAD = 0x15
const ILOAD_0 = 0x1a
const ILOAD_1 = 0x1b
const ILOAD_2 = 0x1c
const ILOAD_3 = 0x1d
const IMPDEP1 = 0xfe
const IMPDEP2 = 0xff
const IMUL = 0x68
const INEG = 0x74
const INSTANCEOF = 0xc1
const INVOKEDYNAMIC = 0xba
const INVOKEINTERFACE = 0xb9
const INVOKESPECIAL = 0xb7
const INVOKESTATIC = 0xb8
const INVOKEVIRTUAL = 0xb6
const IOR = 0x80
const IREM = 0x70
const IRETURN = 0xac
const ISHL = 0x78
const ISHR = 0x7a
const ISTORE = 0x36
const ISTORE_0 = 0x3b
const ISTORE_1 = 0x3c
const ISTORE_2 = 0x3d
const ISTORE_3 = 0x3e
const ISUB = 0x64
const IUSHR = 0x7c
const IXOR = 0x82
const JSR = 0xa8
const JSR_W = 0xc9
const L2D = 0x8a
const L2F = 0x89
const L2I = 0x88
const LADD = 0x61
const LALOAD = 0x2f
const LAND = 0x7f
const LASTORE = 0x50
const LCMP = 0x94
const LCONST_0 = 0x09
const LCONST_1 = 0x0a
const LDC = 0x12
const LDC2_W = 0x14
const LDIV = 0x6d
const LLOAD = 0x16
const LLOAD_0 = 0x1e
const LLOAD_1 = 0x1f
const LLOAD_2 = 0x20
const LLOAD_3 = 0x21
const LMUL = 0x69
const LNEG = 0x75
const LOOKUPSWITCH = 0xab
const LOR = 0x81
const LREM = 0x71
const LRETURN = 0xad
const LSHL = 0x79
const LSHR = 0x7b
const LSTORE = 0x37
const LSTORE_0 = 0x3f
const LSTORE_1 = 0x40
const LSTORE_2 = 0x41
const LSTORE_3 = 0x42
const LSUB = 0x65
const LUSHR = 0x7d
const LXOR = 0x83
const MONITORENTER = 0xc2
const MONITOREXIT = 0xc3
const MULTINEWARRAY = 0xc5
const NEW = 0xbb
const NEWARRAY = 0xbc
const NOP = 0x00
const POP = 0x57
const POP2 = 0x58
const PUTFIELD = 0xb5
const PUTSTATIC = 0xb3
const RET = 0xa9
const RETURN = 0xb1
const SALOAD = 0x35
const SASTORE = 0x56
const SIPUSH = 0x11
const SWAP = 0x5f
const TABLESWITCH = 0xaa
const WIDE = 0xc4
